justsubs/__init__.py
justsubs/manage_subtitles.py
justsubs-0.1.1.dist-info/LICENSE
justsubs-0.1.1.dist-info/METADATA
justsubs-0.1.1.dist-info/WHEEL
justsubs-0.1.1.dist-info/RECORD
