Metadata-Version: 2.1
Name: justsubs
Version: 0.1.1
Summary: Download subtitles from YouTube as plain text.
Home-page: https://github.com/epogrebnyak/justsubs
License: MIT
Author: Evgeny Pogrebnyak
Author-email: e.pogrebnyak@gmail.com
Requires-Python: >=3.10,<4.0
Classifier: License :: OSI Approved :: MIT License
Classifier: Programming Language :: Python :: 3
Classifier: Programming Language :: Python :: 3.10
Classifier: Programming Language :: Python :: 3.11
Classifier: Programming Language :: Python :: 3.12
Requires-Dist: yt-dlp (>=2024.3.10,<2025.0.0)
Project-URL: Repository, https://github.com/epogrebnyak/justsubs
